lab2/file_reg_top.v
module file_reg_top (
    input wire clk,                    
    input wire we,                     
    input wire [4:0] waddr,           
    input wire [31:0] wdata,         
    input wire [4:0] raddr1,         
    input wire [4:0] raddr2,          
    output wire [31:0] rdata1,        
    output wire [31:0] rdata2         
);

    // Массив регистров: 32 регистра по 32 бита
    reg [31:0] registers [0:31];

    // Синхронная запись
    always @(posedge clk)
        if (we) registers[waddr] <= wdata;

    // Асинхронное чтение с возвратом 0 для адреса 0
    assign rdata1 = (raddr1 == 5'b0) ? 32'h0 : registers[raddr1];
    assign rdata2 = (raddr2 == 5'b0) ? 32'h0 : registers[raddr2];
        

endmodule

lab2/file_reg_top_tb.v
`timescale 1ns/100ps // 1 ns time unit, 100 ps resolution

module file_reg_top_tb;

	reg clk=1;
	always #5 clk = !clk;

    reg we;
    reg [4:0] waddr;
    reg [31:0] wdata;
    reg [4:0] raddr1;
    reg [4:0] raddr2;

    wire [31:0] rdata1;
    wire [31:0] rdata2;

	file_reg_top top0
	(
        .clk(clk),
        .we(we),
        .waddr(waddr),
        .wdata(wdata),
        .raddr1(raddr1),
        .raddr2(raddr2),
        .rdata1(rdata1),
        .rdata2(rdata2)
	);

	initial begin
		$dumpfile("wave.vcd");		// create a VCD waveform dump called "wave.vcd"
		$dumpvars(0, file_reg_top_tb);		// dump variable changes in the testbench

        we <= 0;
        waddr <= 0;
        wdata <= 0;
        raddr1 <= 0;
        raddr2 <= 0;
		

        @(posedge clk);
        we <= 1;
        waddr <= 0;
        wdata <= 32'hDEADBEEF;
        @(posedge clk);
        we <= 0;
        @(posedge clk);


        we <= 1;
        waddr <= 1;
        wdata <= 32'hCAFEBABE;
        @(posedge clk);
        we <= 0;
        raddr1 <= 0;
        raddr2 <= 1;
        @(posedge clk);


        we <= 1;
        waddr <= 2;
        wdata <= 32'h12345678;
        @(posedge clk);
        we <= 0;
        raddr1 <= 2;
        raddr2 <= 0;
        @(posedge clk);


        raddr1 <= 0;
        raddr2 <= 0;
        @(posedge clk);


        raddr1 <= 1;
        raddr2 <= 2;
        @(posedge clk);

        raddr1 <= 2;
        raddr2 <= 1;
        @(posedge clk);

        we <= 1;
        waddr <= 2;
        wdata <= 32'h87654321;
        @(posedge clk);
        we <= 0;
        raddr1 <= 2;
        raddr2 <= 2;
        @(posedge clk);




		$finish;
		
	end

    initial begin
        $monitor("t=%0t: we=%b, waddr=%h, wdata=%h, raddr1=%h, rdata1=%h, raddr2=%h, rdata2=%h",
                 $time, we, waddr, wdata, raddr1, rdata1, raddr2, rdata2);
    end

endmodule

lab2/wave.vcd
$date
	Fri Oct 10 14:39:15 2025
$end
$version
	Icarus Verilog
$end
$timescale
	100ps
$end
$scope module file_reg_top_tb $end
$var wire 32 ! rdata2 [31:0] $end
$var wire 32 " rdata1 [31:0] $end
$var reg 1 # clk $end
$var reg 5 $ raddr1 [4:0] $end
$var reg 5 % raddr2 [4:0] $end
$var reg 5 & waddr [4:0] $end
$var reg 32 ' wdata [31:0] $end
$var reg 1 ( we $end
$scope module top0 $end
$var wire 1 # clk $end
$var wire 5 ) raddr1 [4:0] $end
$var wire 5 * raddr2 [4:0] $end
$var wire 5 + waddr [4:0] $end
$var wire 32 , wdata [31:0] $end
$var wire 1 ( we $end
$var wire 32 - rdata2 [31:0] $end
$var wire 32 . rdata1 [31:0] $end
$upscope $end
$upscope $end
$enddefinitions $end
$comment Show the parameter values. $end
$dumpall
$end
#0
$dumpvars
b0 .
b0 -
b0 ,
b0 +
b0 *
b0 )
0(
b0 '
b0 &
b0 %
b0 $
1#
b0 "
b0 !
$end
#50
0#
#100
b11011110101011011011111011101111 '
b11011110101011011011111011101111 ,
1(
1#
#150
0#
#200
0(
1#
#250
0#
#300
b11001010111111101011101010111110 '
b11001010111111101011101010111110 ,
b1 &
b1 +
1(
1#
#350
0#
#400
b11001010111111101011101010111110 !
b11001010111111101011101010111110 -
b1 %
b1 *
0(
1#
#450
0#
#500
b10010001101000101011001111000 '
b10010001101000101011001111000 ,
b10 &
b10 +
1(
1#
#550
0#
#600
b0 !
b0 -
b10010001101000101011001111000 "
b10010001101000101011001111000 .
b0 %
b0 *
b10 $
b10 )
0(
1#
#650
0#
#700
b0 "
b0 .
b0 $
b0 )
1#
#750
0#
#800
b10010001101000101011001111000 !
b10010001101000101011001111000 -
b11001010111111101011101010111110 "
b11001010111111101011101010111110 .
b10 %
b10 *
b1 $
b1 )
1#
#850
0#
#900
b11001010111111101011101010111110 !
b11001010111111101011101010111110 -
b10010001101000101011001111000 "
b10010001101000101011001111000 .
b1 %
b1 *
b10 $
b10 )
1#
#950
0#
#1000
b10000111011001010100001100100001 '
b10000111011001010100001100100001 ,
1(
1#
#1050
0#
#1100
b10000111011001010100001100100001 !
b10000111011001010100001100100001 -
b10000111011001010100001100100001 "
b10000111011001010100001100100001 .
b10 %
b10 *
0(
1#
